{
  "name": "5_6",
  "initial_state": {
    "stacks": [
      ["A", "D", "F", "C"],
      ["B", "E"],
      [],
      []
    ],
    "holding": null,
    "robot_status": "idle"
  },
  "goal": {
    "description": "Build the following three towers from bottom to top: A-B, C-E, D-F.",
    "target_configurations": [
      ["A", "B"],
      [],
      ["C", "E"],
      ["D", "F"]
    ]
  },
  "constraint_set": "partial_observability",
  "metadata": {
    "category": "5",
    "min_steps": 12,
    "non_constructive_steps": 2,
    "num_blocks": 6,
    "num_stacks": 4,
    "misplaced_blocks": 5
  }
}
